deprecated/__init__.py
deprecated/classic.py
deprecated/sphinx.py
Deprecated-1.2.15.dist-info/LICENSE.rst
Deprecated-1.2.15.dist-info/METADATA
Deprecated-1.2.15.dist-info/WHEEL
Deprecated-1.2.15.dist-info/top_level.txt
Deprecated-1.2.15.dist-info/RECORD
