Metadata-Version: 2.1
Name: Deprecated
Version: 1.2.15
Summary: Python @deprecated decorator to deprecate old python classes, functions or methods.
Home-page: https://github.com/laurent-laporte-pro/deprecated
Author: Laurent LAPORTE
Author-email: laurent.laporte.pro@gmail.com
License: MIT
Project-URL: Documentation, https://deprecated.readthedocs.io/en/latest/
Project-URL: Source, https://github.com/laurent-laporte-pro/deprecated
Project-URL: Bug Tracker, https://github.com/laurent-laporte-pro/deprecated/issues
Keywords: deprecate,deprecated,deprecation,warning,warn,decorator
Platform: any
Classifier: Development Status :: 5 - Production/Stable
Classifier: Environment :: Web Environment
Classifier: Intended Audience :: Developers
Classifier: License :: OSI Approved :: MIT License
Classifier: Operating System :: OS Independent
Classifier: Programming Language :: Python
Classifier: Programming Language :: Python :: 2
Classifier: Programming Language :: Python :: 2.7
Classifier: Programming Language :: Python :: 3
Classifier: Programming Language :: Python :: 3.4
Classifier: Programming Language :: Python :: 3.5
Classifier: Programming Language :: Python :: 3.6
Classifier: Programming Language :: Python :: 3.7
Classifier: Programming Language :: Python :: 3.8
Classifier: Programming Language :: Python :: 3.9
Classifier: Programming Language :: Python :: 3.10
Classifier: Programming Language :: Python :: 3.11
Classifier: Programming Language :: Python :: 3.12
Classifier: Topic :: Software Development :: Libraries :: Python Modules
Requires-Python: >=2.7, !=3.0.*, !=3.1.*, !=3.2.*, !=3.3.*
License-File: LICENSE.rst
Requires-Dist: wrapt<2,>=1.10
Provides-Extra: dev
Requires-Dist: tox; extra == "dev"
Requires-Dist: PyTest; extra == "dev"
Requires-Dist: PyTest-Cov; extra == "dev"
Requires-Dist: bump2version<1; extra == "dev"
Requires-Dist: sphinx<2; extra == "dev"
Requires-Dist: jinja2~=3.0.3; extra == "dev"
Requires-Dist: setuptools; python_version >= "3.12" and extra == "dev"
